audio_cast/__init__.py
audio_cast/discoverer_devices.py
audio_cast/discoverer_media.py
audio_cast/endpoints.py
audio_cast/player.py
audio_cast/utils.py
audio_cast/scripts/__init__.py
audio_cast/scripts/command.py
audio_cast-0.0.16.dist-info/COPYING
audio_cast-0.0.16.dist-info/METADATA
audio_cast-0.0.16.dist-info/WHEEL
audio_cast-0.0.16.dist-info/entry_points.txt
audio_cast-0.0.16.dist-info/top_level.txt
audio_cast-0.0.16.dist-info/RECORD
